{"sections":{"heading":{"type":"main-collection-banner","custom_css":[],"settings":{"top_spacing":"small","width":"page-width","texts_aligment":"text-left"}},"description":{"type":"main-collection-description","settings":{"no_header_spacing":true,"top_spacing":"small","width":"page-width","texts_aligment":"text-left"}},"product-grid":{"type":"main-collection-product-grid","settings":{"top_spacing":"medium","width":"page-width","grid":"col-st-6 col-3","mobile_grid":"12","enable_filtering":"horizontal","enable_sorting":true,"enable_sticky_filter_button":true,"enable_products_count":true,"pagination_aligment":"text-center","product_limit":18,"image_ratio":"1","show_secondary_image":false,"texts_aligment":"text-center","product_name_size":"body2","show_vendor":false,"show_type":false,"show_rating":true,"show_price":true,"truncate_product_name":false,"hover_underline":false,"button_type_product":"show","show_button_quickview":false,"show_badge_on_sale":true,"show_badge_sold_out":true,"show_badge_feature":true}},"172f76e6-ca14-490c-8834-23d69db8e6d7":{"type":"recently-viewed-products","settings":{"subheading":"","heading":"Recently viewed products","heading_aligment":"text-center","top_spacing":"normal","width":"page-width","grid":"col-st-6 col-3","mobile_grid":"12","swipe_on_mobile":true,"image_ratio":"1","show_secondary_image":true,"texts_aligment":"text-center","product_name_size":"body2","show_vendor":true,"show_price":true,"truncate_product_name":false,"hover_underline":false,"show_button_quickview":true,"show_badge_on_sale":true,"show_badge_sold_out":true,"show_badge_feature":true,"color_subheading":"rgba(0,0,0,0)","color_heading":"rgba(0,0,0,0)","color_meta":"rgba(0,0,0,0)"}}},"order":["heading","description","product-grid","172f76e6-ca14-490c-8834-23d69db8e6d7"]}